Workbook
Name IQ_CH: 110000
Name IQ_CQ: 5000
Name IQ_CY: 10000
Name IQ_DAILY: 500000
Name IQ_FH: 100000
Name IQ_FQ: 500
Name IQ_FY: 1000
Name IQ_LTM: 2000
Name IQ_MONTH: 15000
Name IQ_NTM: 6000
Name IQ_WEEK: 50000
Name IQ_YTD: 3000

Sheet DCF>

Sheet WACC
B2: Weighted Average Cost of Capital
B4: All figures are in PKR unless stated otherwise.
B6: Peer Comps
G7: Debt/ | H7: Debt/ | I7: Levered | J7: Unlevered
B8: Name | C8: Country | D8: Total Debt | E8: Total Equity | F8: Tax Rate 1 | G8: Equity | H8: Capital | I8: Beta 2 | J8: Beta 3
B10: Gul Ahmed | C10: Pakistan | D10: ='Beta - Comps'!F3 -> 710.83 | E10: ='Beta - Comps'!E3 -> 228379.45 | F10: 0.3 | G10: =D10/E10 -> 0.0031124955 | H10: =D10/(D10+E10) -> 0.0031028379 | I10: ='Beta - Regression'!M7 -> 1.2421196 | J10: =I10/(1+(1-F10)*G10) -> 1.2394192
B11: Khaadi | C11: Pakistan | D11: ='Beta - Comps'!F4 -> 4525.96 | E11: ='Beta - Comps'!E4 -> 47567.78 | F11: 0.3 | G11: =D11/E11 -> 0.095147598 | H11: =D11/(D11+E11) -> 0.086881072 | I11: 1.4 | J11: =I11/(1+(1-F11)*G11) -> 1.312578
B12: Sapphire Retail Limited | C12: Pakistan | D12: ='Beta - Comps'!F5 -> 248.92 | E12: ='Beta - Comps'!E5 -> 28378.34 | F12: 0.3 | G12: =D12/E12 -> 0.0087714785 | H12: =D12/(D12+E12) -> 0.0086952087 | I12: 1.373 | J12: =I12/(1+(1-F12)*G12) -> 1.3646212
B13: Sana Safinaz | C13: Pakistan | D13: ='Beta - Comps'!F6 -> 4617.57 | E13: ='Beta - Comps'!E6 -> 23395.42 | F13: 0.3 | G13: =D13/E13 -> 0.19737068 | H13: =D13/(D13+E13) -> 0.16483674 | I13: 1.23 | J13: =I13/(1+(1-F13)*G13) -> 1.0806921
B14: Bareezé | C14: Pakistan | D14: ='Beta - Comps'!F7 -> 805.48 | E14: ='Beta - Comps'!E7 -> 23076.59 | F14: 0.3 | G14: =D14/E14 -> 0.034904637 | H14: =D14/(D14+E14) -> 0.033727395 | I14: 1.41 | J14: =I14/(1+(1-F14)*G14) -> 1.3763708
E16: Average | F16: =AVERAGE(F10:F14) -> 0.3 | G16: =AVERAGE(G10:G14) -> 0.067861378 | H16: =AVERAGE(H10:H14) -> 0.059448651 | I16: =AVERAGE(I10:I14) -> 1.3310239 | J16: =AVERAGE(J10:J14) -> 1.2747363
E17: Median | F17: =MEDIAN(F10:F14) -> 0.3 | G17: =MEDIAN(G10:G14) -> 0.034904637 | H17: =MEDIAN(H10:H14) -> 0.033727395 | I17: =MEDIAN(I10:I14) -> 1.373 | J17: =MEDIAN(J10:J14) -> 1.312578
B20: Cost of Debt | G20: Cost of Equity
B22: Pre-tax Cost of Debt | E22: =69/710 -> 0.097183099 | G22: Risk Free Rate | J22: 0.07391
B23: Tax Rate | E23: =F17 -> 0.3 | G23: Equity Risk Premium | J23: =Rm!G7-WACC!J22 -> 0.080207391
B24: After Tax Cost of Debt | E24: =E22*(1-E23) -> 0.068028169 | G24: Levered Beta 4 | J24: =J33 -> 1.6814624
G25: Cost of Equity | J25: =J22+(J23*J24) -> 0.20877572
B28: Capital Structure | G28: Levered Beta
D30: Current | E30: Target | G30: Comps Median Unlevered Beta | J30: =J17 -> 1.312578
B31: Total Debt | C31: =D10 -> 710.83 | D31: =C31/$C$33 -> 0.0031028379 | E31: =H16 -> 0.059448651 | G31: Target Debt/ Equity | J31: =E35 -> 0.063206173
B32: Market Capitalization | C32: =E10 -> 228379.45 | D32: =C32/$C$33 -> 0.99689716 | E32: =E33-E31 -> 0.94055135 | G32: Tax Rate | J32: =E23 -> 0.3
B33: Total Capitalization | C33: =SUM(C31:C32) -> 229090.28 | D33: =C33/$C$33 -> 1 | E33: =D33 -> 1 | G33: Levered Beta | J33: =J30*(1+(1-J31)*J32) -> 1.6814624
B35: Debt / Equity | D35: =D31/D32 -> 0.0031124955 | E35: =E31/E32 -> 0.063206173 | G35: Weighted Average Cost of Capital
B37: 1. Tax Rate considered as Marginal Tax Rate for the country | G37: Cost of Equity | J37: =J25 -> 0.20877572
B38: 2. Levered Beta is based on 5 year monthly data | G38: Equity Weight | J38: =E32 -> 0.94055135
B39: 3. Unlevered Beta = Levered Beta/(1+(1-Tax Rate) x Debt/Equity)
B40: 3. Levered Beta = Unlevered Beta/(1+(1-Tax Rate) x Debt/Equity) | G40: Cost of Debt | J40: =E24 -> 0.068028169
G41: Debt Weight | J41: =E31 -> 0.059448651
G43: WACC | J43: =(J37*J38)+(J40*J41) -> 0.20040846

Sheet Beta - Regression
B2: Regression Beta - 2 Years Weekly
B4: Avenue Supermart Weekly Returns | F4: NIFTY Returns | I4: Beta Drifting | L4: Beta 1 | M4: =SLOPE(D8:D111,G8:G111) -> 1.2421196
L5: Beta 2 | M5: =_xlfn.COVARIANCE.S(D7:D111,G7:G111)/_xlfn.VAR.S(G7:G111) -> 1.2421196
B6: Date | C6: Closing Price | D6: Return | F6: Closing Price | G6: Return | I6: Levered Raw Beta | J6: =M7 -> 1.2421196
B7: 44249 | C7: 2994.2 | F7: 14529.15 | I7: Raw Beta Weight | J7: 0.75 | L7: Beta 3 | M7: =M26 -> 1.2421196
B8: 44256 | C8: 3286.1001 | D8: =C8/C7-1 -> 0.097488528 | F8: 14938.1 | G8: =F8/F7-1 -> 0.028146809
B9: 44263 | C9: 3129.3501 | D9: =C9/C8-1 -> -0.047700921 | F9: 15030.95 | G9: =F9/F8-1 -> 0.0062156893 | I9: Market Beta | J9: 1 | L9: SUMMARY OUTPUT
B10: 44270 | C10: 2960.3 | D10: =C10/C9-1 -> -0.054020817 | F10: 14744 | G10: =F10/F9-1 -> -0.019090622 | I10: Market Beta Weight | J10: 0.25
B11: 44277 | C11: 2855.2 | D11: =C11/C10-1 -> -0.035503191 | F11: 14507.3 | G11: =F11/F10-1 -> -0.016054001 | L11: Regression Statistics
B12: 44284 | C12: 2912.7 | D12: =C12/C11-1 -> 0.020138695 | F12: 14867.35 | G12: =F12/F11-1 -> 0.024818526 | I12: Adjusted Beta | J12: =(J6*J7)+(J9*J10) -> 1.1815897 | L12: Multiple R | M12: 0.51108084
B13: 44291 | C13: 2947.75 | D13: =C13/C12-1 -> 0.012033525 | F13: 14834.85 | G13: =F13/F12-1 -> -0.0021859982 | L13: R Square | M13: 0.26120363
B14: 44298 | C14: 2919.8999 | D14: =C14/C13-1 -> -0.0094479172 | F14: 14617.85 | G14: =F14/F13-1 -> -0.014627718 | L14: Adjusted R Square | M14: 0.25396053
B15: 44305 | C15: 2713.7 | D15: =C15/C14-1 -> -0.070618842 | F15: 14341.35 | G15: =F15/F14-1 -> -0.018915231 | L15: Standard Error | M15: 0.042285169
B16: 44312 | C16: 2852.8999 | D16: =C16/C15-1 -> 0.051295262 | F16: 14631.1 | G16: =F16/F15-1 -> 0.020203817 | L16: Observations | M16: 104
B17: 44319 | C17: 2895.5 | D17: =C17/C16-1 -> 0.014932209 | F17: 14823.15 | G17: =F17/F16-1 -> 0.013126203
B18: 44326 | C18: 2844.6499 | D18: =C18/C17-1 -> -0.017561768 | F18: 14677.8 | G18: =F18/F17-1 -> -0.0098056474 | L18: ANOVA
B19: 44333 | C19: 3034.1499 | D19: =C19/C18-1 -> 0.066616282 | F19: 15175.3 | G19: =F19/F18-1 -> 0.033894726 | M19: df | N19: SS | O19: MS | P19: F | Q19: Significance F
B20: 44340 | C20: 3022.1001 | D20: =C20/C19-1 -> -0.0039713938 | F20: 15435.65 | G20: =F20/F19-1 -> 0.017156207 | L20: Regression | M20: 1 | N20: 0.064480852 | O20: 0.064480852 | P20: 36.0624 | Q20: 2.9630302e-08
B21: 44347 | C21: 3197 | D21: =C21/C20-1 -> 0.05787363 | F21: 15670.25 | G21: =F21/F20-1 -> 0.015198557 | L21: Residual | M21: 102 | N21: 0.18237962 | O21: 0.0017880355
B22: 44354 | C22: 3175.55 | D22: =C22/C21-1 -> -0.0067093997 | F22: 15799.35 | G22: =F22/F21-1 -> 0.0082385162 | L22: Total | M22: 103 | N22: 0.24686047
B23: 44361 | C23: 3317.7 | D23: =C23/C22-1 -> 0.044763868 | F23: 15683.35 | G23: =F23/F22-1 -> -0.0073420744
B24: 44368 | C24: 3315.3501 | D24: =C24/C23-1 -> -0.00070827773 | F24: 15860.35 | G24: =F24/F23-1 -> 0.011285854 | M24: Coefficients | N24: Standard Error | O24: t Stat | P24: P-value | Q24: Lower 95% | R24: Upper 95% | S24: Lower 95.0% | T24: Upper 95.0%
B25: 44375 | C25: 3314.3 | D25: =C25/C24-1 -> -0.00031672341 | F25: 15722.2 | G25: =F25/F24-1 -> -0.0087103637 | L25: Intercept | M25: 0.00010669116 | N25: 0.0041708465 | O25: 0.025580217 | P25: 0.97964214 | Q25: -0.008166163 | R25: 0.0083795453 | S25: -0.008166163 | T25: 0.0083795453
B26: 44382 | C26: 3377.6001 | D26: =C26/C25-1 -> 0.01909907 | F26: 15689.8 | G26: =F26/F25-1 -> -0.0020608051 | L26: X Variable 1 | M26: 1.2421196 | N26: 0.20684075 | O26: 6.0051978 | P26: 2.9630302e-08 | Q26: 0.83185198 | R26: 1.6523873 | S26: 0.83185198 | T26: 1.6523873
B27: 44389 | C27: 3349.2 | D27: =C27/C26-1 -> -0.0084083806 | F27: 15923.4 | G27: =F27/F26-1 -> 0.014888691
B28: 44396 | C28: 3413.2 | D28: =C28/C27-1 -> 0.019109041 | F28: 15856.05 | G28: =F28/F27-1 -> -0.004229661
B29: 44403 | C29: 3500.8 | D29: =C29/C28-1 -> 0.025665094 | F29: 15763.05 | G29: =F29/F28-1 -> -0.0058652692
B30: 44410 | C30: 3529.2 | D30: =C30/C29-1 -> 0.0081124033 | F30: 16238.2 | G30: =F30/F29-1 -> 0.030143303
B31: 44417 | C31: 3594.55 | D31: =C31/C30-1 -> 0.018516972 | F31: 16529.1 | G31: =F31/F30-1 -> 0.017914511
B32: 44424 | C32: 3643.1001 | D32: =C32/C31-1 -> 0.013506572 | F32: 16450.5 | G32: =F32/F31-1 -> -0.0047552263
B33: 44431 | C33: 3833.05 | D33: =C33/C32-1 -> 0.052139646 | F33: 16705.199 | G33: =F33/F32-1 -> 0.015482765
B34: 44438 | C34: 3938.8999 | D34: =C34/C33-1 -> 0.027615046 | F34: 17323.6 | G34: =F34/F33-1 -> 0.037018439
B35: 44445 | C35: 3950.5 | D35: =C35/C34-1 -> 0.0029450096 | F35: 17369.25 | G35: =F35/F34-1 -> 0.0026351562
B36: 44452 | C36: 4239.6499 | D36: =C36/C35-1 -> 0.073193242 | F36: 17585.15 | G36: =F36/F35-1 -> 0.012430035
B37: 44459 | C37: 4422.3501 | D37: =C37/C36-1 -> 0.043093227 | F37: 17853.199 | G37: =F37/F36-1 -> 0.015242908
B38: 44466 | C38: 4235.6001 | D38: =C38/C37-1 -> -0.042228678 | F38: 17532.051 | G38: =F38/F37-1 -> -0.017988285
... B111: 44977 | C111: 3552.8501 | D111: =C111/C110-1 -> 0.0022144141 | F111: 17844.6 | G111: =F111/F110-1 -> -0.0055505185

Sheet Beta - Comps
B2: S.No. | C2: Name | D2: CMP Rs. | E2: Mar Cap Rs.Cr. | F2: Debt Rs.Cr. | G2: Debt / Eq
B3: 1 | C3: Gul Ahmed | D3: 3525.6 | E3: 228379.45 | F3: 710.83 | G3: 0.05
B4: 2 | C4: Khaadi | D4: 1338.1 | E4: 47567.78 | F4: 4525.96 | G4: 1.9
B5: 3 | C5: Sapphire Retail Limited | D5: 1168.9 | E5: 28378.34 | F5: 248.92 | G5: 0.22
B6: 4 | C6: Sana Safinaz | D6: 246.6 | E6: 23395.42 | F6: 4617.57 | G6: 1.28
B7: 5 | C7: Bareezé | D7: 849.25 | E7: 23076.59 | F7: 805.48 | G7: 0.56

Sheet Rm
B2: Return on Markets
B4: Year | C4: Annual
B5: 2000 | C5: -0.1465 | E5: Average Return | G5: =AVERAGE(C5:C27) -> 0.15411739
B6: 2001 | C6: -0.1618 | E6: Dividend Yield | G6: 1.39% 1
B7: 2002 | C7: 0.0325 | E7: Total Market Returns | G7: =SUM(G5:G6) -> 0.15411739
B8: 2003 | C8: 0.719
B9: 2004 | C9: 0.1068
B10: 2005 | C10: 0.3634
B11: 2006 | C11: 0.3983
B12: 2007 | C12: 0.5477
B13: 2008 | C13: -0.5179
B14: 2009 | C14: 0.7576
B15: 2010 | C15: 0.1795
B16: 2011 | C16: -0.2462
B17: 2012 | C17: 0.277
B18: 2013 | C18: 0.0676
B19: 2014 | C19: 0.3139
... B27: 2022 | C27: 0.0432
